bert_pretty/__init__.py
bert_pretty/setup.py
bert_pretty/test_gpt.py
bert_pretty/test_py.py
bert_pretty/test_t5.py
bert_pretty/test_unilm.py
bert_pretty/tokenization.py
bert_pretty/autoregressive/__init__.py
bert_pretty/cls/__init__.py
bert_pretty/feature/__init__.py
bert_pretty/feature/legend.py
bert_pretty/feature/pad.py
bert_pretty/feature/tokenization_map.py
bert_pretty/ner/__init__.py
bert_pretty/ner/labels.py
bert_pretty/ner/ner_crf_decode_utils.py
bert_pretty/ner/ner_pointer_double.py
bert_pretty/ner/ner_pointer_full.py
bert_pretty/ner/utils.py
bert_pretty/relation/__init__.py
bert_pretty-0.1.0.post0.dist-info/METADATA
bert_pretty-0.1.0.post0.dist-info/WHEEL
bert_pretty-0.1.0.post0.dist-info/top_level.txt
bert_pretty-0.1.0.post0.dist-info/RECORD
